MANIFEST.in
README
setup.cfg
setup.py
sphinxcontrib/__init__.py
sphinxcontrib/googlemaps.py
sphinxcontrib_googlemaps.egg-info/PKG-INFO
sphinxcontrib_googlemaps.egg-info/SOURCES.txt
sphinxcontrib_googlemaps.egg-info/dependency_links.txt
sphinxcontrib_googlemaps.egg-info/namespace_packages.txt
sphinxcontrib_googlemaps.egg-info/not-zip-safe
sphinxcontrib_googlemaps.egg-info/requires.txt
sphinxcontrib_googlemaps.egg-info/top_level.txt