Metadata-Version: 1.1
Name: sphinxcontrib-googlemaps
Version: 0.1.0
Summary: Sphinx "googlemaps" extension
Home-page: http://bitbucket.org/birkenfeld/sphinx-contrib
Author: Takeshi KOMIYA
Author-email: i.tkomiya@gmail.com
License: BSD
Download-URL: http://pypi.python.org/pypi/sphinxcontrib-googlemaps
Platform: any
Classifier: Development Status :: 4 - Beta
Classifier: Environment :: Console
Classifier: Environment :: Web Environment
Classifier: Intended Audience :: Developers
Classifier: License :: OSI Approved :: BSD License
Classifier: Operating System :: OS Independent
Classifier: Programming Language :: Python
Classifier: Topic :: Documentation
Classifier: Topic :: Utilities
